monokaki/__init__.py
monokaki/renderer.py
monokaki-0.1.1.dist-info/DESCRIPTION.rst
monokaki-0.1.1.dist-info/entry_points.txt
monokaki-0.1.1.dist-info/METADATA
monokaki-0.1.1.dist-info/metadata.json
monokaki-0.1.1.dist-info/RECORD
monokaki-0.1.1.dist-info/top_level.txt
monokaki-0.1.1.dist-info/WHEEL
