Metadata-Version: 2.0
Name: monokaki
Version: 0.1.1
Summary: contextual logging library, no patch, no logging module replacement
Home-page: https://github.com/podhmo/monokaki
Author: podhmo
Author-email: UNKNOWN
License: UNKNOWN
Keywords: logging structured-logging contextual-logging
Platform: UNKNOWN
Classifier: Programming Language :: Python
Classifier: Programming Language :: Python :: Implementation :: CPython
Provides-Extra: docs
Provides-Extra: testing
